OneWire.py
onion_w1_sysfs-0.1.6.dist-info/LICENSE.md
onion_w1_sysfs-0.1.6.dist-info/METADATA
onion_w1_sysfs-0.1.6.dist-info/WHEEL
onion_w1_sysfs-0.1.6.dist-info/top_level.txt
onion_w1_sysfs-0.1.6.dist-info/RECORD
