Metadata-Version: 2.1
Name: onion-w1-sysfs
Version: 0.1.6
Summary: w1 lib using the sysfs interface
Home-page: https://github.com/grizmin/w1-gpio-linux
Author: Grizmin
Author-email: grizmin@gmail.com
License: UNKNOWN
Keywords: onion omega IoT w1 onewire 1w
Platform: UNKNOWN
Classifier: Programming Language :: Python :: 3
Classifier: License :: OSI Approved :: GNU General Public License v3 (GPLv3)
Classifier: Operating System :: OS Independent
Classifier: Programming Language :: Python :: 3
Classifier: Programming Language :: Python :: 3.5
Classifier: Programming Language :: Python :: 3.6
Classifier: Programming Language :: Python :: 3.7
Classifier: Programming Language :: Python :: 3.8
Requires-Python: !=3.0.*, !=3.1.*, !=3.2.*, !=3.3.*, !=3.4.*, <4
